alegra/__init__.py
alegra/client.py
alegra/config.py
alegra/models/__init__.py
alegra/models/address.py
alegra/models/company.py
alegra/models/customer.py
alegra/models/dian.py
alegra/models/invoice.py
alegra/models/payroll.py
alegra/models/phone_number.py
alegra/models/test_set.py
alegra/resources/__init__.py
alegra/resources/base.py
alegra/resources/factory.py
e_provider_alegra-0.0.1.dist-info/METADATA
e_provider_alegra-0.0.1.dist-info/WHEEL
e_provider_alegra-0.0.1.dist-info/top_level.txt
e_provider_alegra-0.0.1.dist-info/RECORD
