Metadata-Version: 2.2
Name: e-provider-alegra
Version: 0.0.1
Summary: Python SDK for Alegra API
Author: Luis Martinez
Requires-Python: >=3.6
Requires-Dist: pydantic[email]==2.8.2
Requires-Dist: requests==2.32.3
Requires-Dist: httpx==0.27.2
Dynamic: author
Dynamic: requires-dist
Dynamic: requires-python
Dynamic: summary
